LICENSE
MANIFEST.in
README.md
setup.cfg
setup.py
devicehive/__init__.py
devicehive/api.py
devicehive/api_event.py
devicehive/api_handler.py
devicehive/api_request.py
devicehive/api_response.py
devicehive/command.py
devicehive/device.py
devicehive/device_hive.py
devicehive/device_hive_api.py
devicehive/device_type.py
devicehive/handler.py
devicehive/network.py
devicehive/notification.py
devicehive/subscription.py
devicehive/token.py
devicehive/user.py
devicehive.egg-info/PKG-INFO
devicehive.egg-info/SOURCES.txt
devicehive.egg-info/dependency_links.txt
devicehive.egg-info/requires.txt
devicehive.egg-info/top_level.txt
devicehive/data_formats/__init__.py
devicehive/data_formats/data_format.py
devicehive/data_formats/json_data_format.py
devicehive/handlers/__init__.py
devicehive/handlers/handler.py
devicehive/transports/__init__.py
devicehive/transports/http_transport.py
devicehive/transports/transport.py
devicehive/transports/websocket_transport.py